{
  "meta": {
    "title": "AlegreMente 2025 · Escena 3",
    "subtitle": "Carnaval / Pueblo Tambor / Siyahamba",
    "footer": "AlegreMente 2025 · Escena 3 · Guía práctica",
    "images": {
      "hero": "Escena 3.jpg",
      "heroAlt": "Escena 3 – Carnaval / Pueblo Tambor / Siyahamba",
      "logo": "logo.jpg"
    }
  },

  "audio": {
    "label": "🎶 Audios de la escena",
    "sources": ["Siyahamba.mp3"],
    "adicionales": [
      { "title": "Danza · Son de Negro", "src": "DANZA ESCENA 3 Son de Negro.m4a" }
    ]
  },

  "filters": {
    "areas": ["teatro","musica","danza","plastica","luces","sonido","produccion"],
    "centros": ["arroyo","betania","colegio"],
    "log": ["vestuario","sonido","orquesta","proyeccion","materiales","luces","percusion"]
  },

  "resumen": {
    "text": "Sofía vuelve a latir con el <em>nosotros</em>. En <b>Siyahamba / Pueblo Tambor</b> el carnaval despierta, los tambores llaman y el grupo grita: <em>“¡Caminamos juntos!”</em>",
    "duration": "10 min",
    "tags": ["Teatro · Danza · Artes Plásticas", "Música: Orquesta + Tambores"]
  },

  "proposito": [
    "<strong>Reforzar</strong> sentido de pertenencia y comunidad a través del arte.",
    "<strong>Explorar</strong> ritmos afro y cantos colectivos como lenguaje de unión.",
    "<strong>Valorar</strong> la diversidad cultural y los símbolos del carnaval."
  ],

  "pasos": [
    "Sofía encuentra un círculo silencioso con rostros pintados y trajes de carnaval.",
    "Diálogo del grupo: “Esta es nuestra piel de carnaval… pero perdimos la música”.",
    "Golpes al suelo: <b>Tum… Tum… ¡TUM!</b> y el círculo comienza a moverse.",
    "La <b>orquesta</b> entra con <em>Siyahamba</em> y se suma <em>Pueblo Tambor</em>.",
    "Clímax en espiral y grito final: <b>“¡Caminamos juntos!”</b>"
  ],

  "plastica": {
    "items": [
      "<strong>Tambor gigante</strong> de tela en el centro del escenario.",
      "<strong>Máscaras</strong> de carnaval (colgadas, proyectadas y en varillas).",
      "<strong>Fondo</strong> cálido con motivos de carnaval (<code>Fondo 3.jpg</code>).",
      "<strong>Maquillaje artístico</strong> con diseños afro y colores vivos."
    ],
    "assets": [
      { "src": "Fondo 3.jpg" },
      { "src": "escenario3.png" },
      { "src": "Escena 3.jpg" },
      { "src": "logo.jpg" }
    ]
  },

  "luces": [
    { "Cue":"<b>L1 – Llamado</b>", "Estado":"Ámbar tenue + azul bajo", "Detalle":"Círculo silencioso" },
    { "Cue":"<b>L2 – Primer Tum</b>", "Estado":"Ámbar medio + contraluces", "Detalle":"Sombras de máscaras" },
    { "Cue":"<b>L3 – Carnaval</b>", "Estado":"Cálidos vivos", "Detalle":"Inicio de Siyahamba" },
    { "Cue":"<b>L4 – Espiral</b>", "Estado":"Movimiento suave", "Detalle":"Barridos cálidos" },
    { "Cue":"<b>L5 – Final</b>", "Estado":"General cálido", "Detalle":"Blackout suave" }
  ],

  "sonido": [
    "<b>Entrada de tambores:</b> tres golpes marcados que activan la escena.",
    "<b>Orquesta:</b> entra tras 8 compases con <em>Siyahamba</em>.",
    "<b>Corte final:</b> limpio para el grito en unísono.",
    "<b>Refuerzo:</b> microfonía/monitores según espacio.",
    "<b>Coordinación A/V:</b> proyección de motivos de carnaval en transiciones."
  ],

  "vestuario": {
    "images": [
      { "title":"Máscaras – opción 1", "src":"mascaras.jpeg", "file":"mascaras.jpeg" },
      { "title":"Vestuario estilo africano – niñas", "src":"vestuario3.jpg", "file":"vestuario3.jpg" }
    ]
  },

  "escenario": {
    "images": [
      { "title":"Arte escena 3", "src":"Escena 3.jpg", "alt":"Arte de Escena 3" },
      { "title":"Tambor", "src":"tambor.jpeg", "alt":"Tambor decorativo" },
      { "title":"Escenario 3", "src":"escenario3.png", "alt":"Layout de escena 3" },
      { "title":"Fondo 3", "src":"Fondo 3.jpg", "alt":"Fondo cálido de carnaval" }
    ]
  },

  "checklist": [
    "[ ] Tambor gigante armado y seguro.",
    "[ ] Máscaras terminadas y listas (colgar / varillas / proyección).",
    "[ ] Maquillaje artístico montado.",
    "[ ] Ensayo orquesta + tambores con conteos claros.",
    "[ ] Cues de luces L1–L5 programados.",
    "[ ] Roles y entradas definidos.",
    "[ ] Proyección de motivos de carnaval operativa."
  ],

  "pdfs": {
    "guion": "Guión Escena III.pdf",
    "partitura": "Siyahamba partitura.pdf"
  },

  "centros": {
    "items": [
      "<b>Teatro:</b> Arroyo – Betania",
      "<b>Danza:</b> Betania",
      "<b>Artes plásticas:</b> GMMMC"
    ],
    "docentesText": "Docentes responsables: Angie Nitola, Leydy Díaz y María Camila Piraján"
  },

  "materiales": [
    "Vestuario <em>estilo africano</em> con colores cálidos. <span class='pill'>vestuario</span>",
    "Tambor de tela (tela quirúrgica, vinilos, pinceles). <span class='pill'>materiales</span>",
    "Máscaras (cartón, pinturas, plumas, lentejuelas, escarcha). <span class='pill'>materiales</span>",
    "Maquillaje artístico (negro, blanco, rojo, verde, amarillo, azul). <span class='pill'>materiales</span>",
    "Proyección: motivos de carnaval (<code>Fondo 3.jpg</code>). <span class='pill'>proyeccion</span>"
  ],

  "recursos": [
    { "title":"Guión Escena III (PDF)", "href":"Guión Escena III.pdf", "areas":["teatro","produccion"], "icon":"📄" },
    { "title":"Partitura – Siyahamba (PDF)", "href":"Siyahamba partitura.pdf", "areas":["musica"], "icon":"🎼" },
    { "title":"Pista – Siyahamba (MP3)", "href":"Siyahamba.mp3", "areas":["musica"], "icon":"🎵" },
    { "title":"Danza – Son de Negro (M4A)", "href":"DANZA ESCENA 3 Son de Negro.m4a", "areas":["danza","musica"], "icon":"🎵" }
  ],

  "docentes": {
    "hint": "Cada docente puede tener su mini guía.",
    "items": [
      { "name":"Angie Nitola", "url":"docentes/teatro.html", "areas":["teatro y artes plásticas"] },
      { "name":"Leydy Díaz", "url":"docentes/teatro.html", "areas":["teatro"] },
      { "name":"María Camila Piraján", "url":"docentes/danza.html", "areas":["danza"] }
    ]
  },

  "glosario": [
    { "term":"cue", "def":"orden/estado de luces o sonido." },
    { "term":"spot", "def":"luz puntual dirigida a una persona/objeto." },
    { "term":"contraluz", "def":"luz desde el fondo para crear siluetas/sombras." }
  ],

  "files": {
    "images": [
      "Escena 3.jpg",
      "escenario3.png",
      "Fondo 3.jpg",
      "mascaras.jpeg",
      "tambor.jpeg",
      "vestuario3.jpg",
      "logo.jpg"
    ],
    "audio": [
      "Siyahamba.mp3",
      "DANZA ESCENA 3 Son de Negro.m4a"
    ],
    "docs": [
      "Guión Escena III.pdf",
      "Siyahamba partitura.pdf"
    ],
    "code": ["index.html", "style.css", "script.js"],
    "data": ["escena3.json"]
  }
}
